pinetopy/__init__.py
pinetopy/fn.py
pinetopy-0.1.5.dist-info/METADATA
pinetopy-0.1.5.dist-info/WHEEL
pinetopy-0.1.5.dist-info/top_level.txt
pinetopy-0.1.5.dist-info/RECORD
