Metadata-Version: 2.1
Name: pinetopy
Version: 0.1.5
Requires-Dist: numpy
Requires-Dist: pandas
Requires-Dist: ta
Requires-Dist: pytz
